odoo/addons/mrp_production_location_picking_type/README.rst
odoo/addons/mrp_production_location_picking_type/__init__.py
odoo/addons/mrp_production_location_picking_type/__manifest__.py
odoo/addons/mrp_production_location_picking_type/i18n/it.po
odoo/addons/mrp_production_location_picking_type/i18n/mrp_production_location_picking_type.pot
odoo/addons/mrp_production_location_picking_type/models/__init__.py
odoo/addons/mrp_production_location_picking_type/models/mrp_production.py
odoo/addons/mrp_production_location_picking_type/models/stock_picking_type.py
odoo/addons/mrp_production_location_picking_type/readme/CONTRIBUTORS.md
odoo/addons/mrp_production_location_picking_type/readme/DESCRIPTION.md
odoo/addons/mrp_production_location_picking_type/readme/USAGE.md
odoo/addons/mrp_production_location_picking_type/static/description/icon.png
odoo/addons/mrp_production_location_picking_type/static/description/index.html
odoo/addons/mrp_production_location_picking_type/tests/__init__.py
odoo/addons/mrp_production_location_picking_type/tests/test_mrp_production_location_picking_type.py
odoo/addons/mrp_production_location_picking_type/views/stock_picking_type_views.xml
odoo_addon_mrp_production_location_picking_type-18.0.1.0.0.3.dist-info/METADATA
odoo_addon_mrp_production_location_picking_type-18.0.1.0.0.3.dist-info/WHEEL
odoo_addon_mrp_production_location_picking_type-18.0.1.0.0.3.dist-info/top_level.txt
odoo_addon_mrp_production_location_picking_type-18.0.1.0.0.3.dist-info/RECORD
